pycontest/__init__.py
pycontest/case.py
pycontest/generator.py
pycontest/helper.py
pycontest/writer.py
pycontest-1.3.dist-info/LICENSE
pycontest-1.3.dist-info/METADATA
pycontest-1.3.dist-info/WHEEL
pycontest-1.3.dist-info/top_level.txt
pycontest-1.3.dist-info/RECORD
