Metadata-Version: 2.1
Name: pycontest
Version: 1.3
Summary: A complete test case generator.
Home-page: https://github.com/matinhimself/pycontest
Author: Matin Habibi
Author-email: aktualled@gmail.com
License: MIT
Platform: UNKNOWN
Requires-Python: >=3.8
License-File: LICENSE
